rubik_sim/__init__.py
rubik_sim/_version.py
rubik_sim/cube.py
rubik_sim/notations.py
rubik_sim-1.0.0.dist-info/LICENSE
rubik_sim-1.0.0.dist-info/METADATA
rubik_sim-1.0.0.dist-info/WHEEL
rubik_sim-1.0.0.dist-info/top_level.txt
rubik_sim-1.0.0.dist-info/RECORD
