Metadata-Version: 2.1
Name: rubik-sim
Version: 1.0.0
Summary: Basic Rubik's cube (3x3) simulator
Author-email: Jaime Gonzalez Gomez <jim.gomez.dnn@gmail.com>
License: MIT license
Project-URL: Source, https://github.com/Jtachan/Rubik_sim.git
Requires-Python: >=3.9
License-File: LICENSE
Requires-Dist: numpy >=1.20
